LICENSE.txt
MANIFEST.in
README.rst
runtests.py
setup.py
pony_indice/__init__.py
pony_indice/admin.py
pony_indice/apps.py
pony_indice/models.py
pony_indice/querysets.py
pony_indice/registry.py
pony_indice/settings.py
pony_indice/signals.py
pony_indice/utils.py
pony_indice/views.py
pony_indice.egg-info/PKG-INFO
pony_indice.egg-info/SOURCES.txt
pony_indice.egg-info/dependency_links.txt
pony_indice.egg-info/top_level.txt
pony_indice/contrib/filters/__init__.py
pony_indice/contrib/filters/filtersets.py
pony_indice/contrib/filters/viewsets.py
pony_indice/contrib/rest_framework/__init__.py
pony_indice/contrib/rest_framework/serializers.py
pony_indice/contrib/rest_framework/viewsets.py
pony_indice/management/__init__.py
pony_indice/management/commands/__init__.py
pony_indice/management/commands/show_indice_registry.py
pony_indice/management/commands/update_indices.py
pony_indice/migrations/0001_initial.py
pony_indice/migrations/__init__.py
pony_indice/tests/__init__.py
pony_indice/tests/factories.py
pony_indice/tests/test_filtersets.py
pony_indice/tests/test_querysets.py
pony_indice/tests/test_registry.py
pony_indice/tests/test_signals.py
pony_indice/tests/test_views.py
pony_indice/tests/test_viewsets.py
pony_indice/tests/testproject/__init__.py
pony_indice/tests/testproject/settings.py
pony_indice/tests/testproject/urls.py
pony_indice/tests/testproject/wsgi.py
pony_indice/tests/testproject/testapp/__init__.py
pony_indice/tests/testproject/testapp/admin.py
pony_indice/tests/testproject/testapp/apps.py
pony_indice/tests/testproject/testapp/models.py
pony_indice/tests/testproject/testapp/tests.py
pony_indice/tests/testproject/testapp/views.py
pony_indice/tests/testproject/testapp/migrations/0001_initial.py
pony_indice/tests/testproject/testapp/migrations/0002_customcallablemodel.py
pony_indice/tests/testproject/testapp/migrations/__init__.py