Metadata-Version: 1.1
Name: pony-indice
Version: 1.0.1
Summary: Search index for Django.
Home-page: https://gitlab.com/ZuluPro/pony-indice
Author: Anthony Monthe (ZuluPro)
Author-email: anthony.monthe@gmail.com
License: BSD License
Platform: UNKNOWN
Classifier: Development Status :: 4 - Beta
Classifier: Environment :: Web Environment
Classifier: Framework :: Django
Classifier: Intended Audience :: Developers
Classifier: License :: OSI Approved :: BSD License
Classifier: Operating System :: OS Independent
Classifier: Programming Language :: Python
Classifier: Programming Language :: Python :: 3
Classifier: Programming Language :: Python :: 3.5
Classifier: Framework :: Django
